doclient/clients/__init__.py
doclient/clients/k8s_client.py
doclient/clients/vpc_client.py
doclient/exceptions/apiexceptions.py
doclient/resources/k8s/schemas.py
doclient/resources/vpc/schemas.py
async_doclient-0.1.3.dist-info/LICENSE
async_doclient-0.1.3.dist-info/METADATA
async_doclient-0.1.3.dist-info/WHEEL
async_doclient-0.1.3.dist-info/RECORD
